{
    "Planned_result": [
        {
            "agentId": 1274,
            "allowDelayTime": 50,
            "altitude": 200,
            "beginTime": 0,
            "endAltitude": 150,
            "endLatitude": 24.7876,
            "endLongitude": 120.906,
            "expectedDuration": 300,
            "latitude": 24.8018,
            "longitude": 120.878,
            "path": [
                {
                    "altitude": 198.27456359402905,
                    "latitude": 24.78344863859793,
                    "longitude": 120.90695477802191,
                    "timestep": 864.0384359962131,
                    "velocity": 5.833333333333333
                },
                {
                    "altitude": 199.88409818174568,
                    "latitude": 24.78232448666445,
                    "longitude": 120.90695449754715,
                    "timestep": 885.4670070584789,
                    "velocity": 5.833333333333333
                },
                {
                    "altitude": 195.6201626356014,
                    "latitude": 24.78232422686889,
                    "longitude": 120.90819267740409,
                    "timestep": 906.895577627751,
                    "velocity": 5.833333333333333
                },
                {
                    "altitude": 153.56174145380697,
                    "latitude": 24.781167,
                    "longitude": 120.909137,
                    "timestep": 928.3241486437266,
                    "velocity": 5.833333333333333
                }
            ],
            "phase_name": 0,
            "status": 0,
            "targetAgentId": 0,
            "task_flag": "p6",
            "task_name": "\u51c6\u5907",
            "task_phase": 6,
            "task_type": 6,
            "velocity": 5.833333333333333
        }
    ],
    "key": "PlanningResults",
    "name": "ResearchGroup5",
    "timestamp": 244.02999999999997
}